gtab/__init__.py
gtab/command_line.py
gtab/core.py
gtab/config/config_cl.json
gtab/config/config_py.json
gtab/config/dir_cl.json
gtab/data/550_cities_and_countries.txt
gtab/data/anchor_candidate_list.txt
gtab/data/internal/freebase/freebase_foods_all.tsv
gtab/data/internal/freebase/freebase_foods_filtered.tsv
gtab/data/internal/freebase/freebase_foods_isdish.tsv
gtab/data/internal/freebase/freebase_foods_isfood.tsv
gtab/data/internal/google_keywords/google_keywords_geo=DE_timeframe=2017-03-05 2021-05-05.pkl
gtab/data/internal/google_keywords/google_keywords_geo=DE_timeframe=2018-03-05 2021-05-05_cat=71.pkl
gtab/data/internal/google_keywords/google_keywords_geo=DE_timeframe=2020-03-05 2021-05-05_cat=71.pkl
gtab/data/internal/google_keywords/google_keywords_geo=IT_timeframe=2019-01-01 2020-08-01.pkl
gtab/data/internal/google_keywords/google_keywords_geo=_timeframe=2019-01-01 2020-08-01.pkl
gtab/data/internal/google_pairs/google_pairs_geo=DE_timeframe=2017-03-05 2021-05-05.pkl
gtab/data/internal/google_pairs/google_pairs_geo=DE_timeframe=2018-03-05 2021-05-05_cat=71.pkl
gtab/data/internal/google_pairs/google_pairs_geo=DE_timeframe=2020-03-05 2021-05-05_cat=71.pkl
gtab/data/internal/google_pairs/google_pairs_geo=IT_timeframe=2019-01-01 2020-08-01.pkl
gtab/data/internal/google_pairs/google_pairs_geo=_timeframe=2019-01-01 2020-08-01.pkl
gtab/data/internal/google_results/google_results_geo=DE_timeframe=2017-03-05 2021-05-05.pkl
gtab/data/internal/google_results/google_results_geo=DE_timeframe=2018-03-05 2021-05-05_cat=71.pkl
gtab/data/internal/google_results/google_results_geo=DE_timeframe=2020-03-05 2021-05-05_cat=71.pkl
gtab/data/internal/google_results/google_results_geo=IT_timeframe=2019-01-01 2020-08-01.pkl
gtab/data/internal/google_results/google_results_geo=_timeframe=2019-01-01 2020-08-01.pkl
gtab/logs/log_geo=DE_timeframe=2017-03-05 2021-05-05.txt
gtab/logs/log_geo=DE_timeframe=2018-03-05 2021-05-05_cat=71.txt
gtab-0.8.dist-info/LICENSE
gtab-0.8.dist-info/METADATA
gtab-0.8.dist-info/WHEEL
gtab-0.8.dist-info/entry_points.txt
gtab-0.8.dist-info/top_level.txt
gtab-0.8.dist-info/RECORD
